sustainer/__main__.py
sustainer/cli.py
sustainer/lib.py
sustainer/main.py
sustainer-0.1.7.dist-info/LICENSE
sustainer-0.1.7.dist-info/METADATA
sustainer-0.1.7.dist-info/WHEEL
sustainer-0.1.7.dist-info/entry_points.txt
sustainer-0.1.7.dist-info/top_level.txt
sustainer-0.1.7.dist-info/RECORD
