Metadata-Version: 2.1
Name: sustainer
Version: 0.1.7
Summary: Keep GPU and CPU temperatures within given limit.
Home-page: https://github.com/james4ever0/sustain_gpu_temperature
License: DO WHAT THE FUCK YOU WANT TO PUBLIC LICENSE 
License-File: LICENSE
Requires-Dist: pynvml
Requires-Dist: xmltodict
Requires-Dist: func-timeout
